modi_flows/README.md
modi_flows/__init__.py
modi_flows/dynamics.py
modi_flows/initialization.py
modi_flows/main.py
modi_flows-0.1.7.dist-info/LICENSE
modi_flows-0.1.7.dist-info/METADATA
modi_flows-0.1.7.dist-info/WHEEL
modi_flows-0.1.7.dist-info/top_level.txt
modi_flows-0.1.7.dist-info/RECORD
