Metadata-Version: 2.1
Name: modi-flows
Version: 0.1.7
Summary: MODI: Multicommodity Optimal Transport-based Dynamics for Image Classification
Author: Alessandro Lonardi, Diego Baptista
Author-email: diego.theuerkauf@tuebingen.mpg.de
Project-URL: homepage, https://github.com/aleable/MODI
Project-URL: bug-tracker, https://github.com/aleable/MODI/issues
Project-URL: repository, https://github.com/aleable/MODI
Keywords: multicommodity,optimal transport,image classification
Classifier: Programming Language :: Python :: 3
Classifier: License :: OSI Approved :: MIT License
Classifier: Operating System :: OS Independent
Requires-Python: >=3.9
License-File: LICENSE
Requires-Dist: numpy >=1.9.3
Requires-Dist: networkx >=2.5.0
Requires-Dist: scipy
Requires-Dist: scikit-image >=0.16.0
Requires-Dist: jupyter
Requires-Dist: pandas
Requires-Dist: tqdm
Requires-Dist: Pillow
Requires-Dist: matplotlib
